CHANGES.rst
CONTRIBUTORS.rst
DEVELOP.rst
LICENSE.rst
MANIFEST.in
README.rst
setup.cfg
setup.py
src/collective/__init__.py
src/collective.slick.egg-info/PKG-INFO
src/collective.slick.egg-info/SOURCES.txt
src/collective.slick.egg-info/dependency_links.txt
src/collective.slick.egg-info/entry_points.txt
src/collective.slick.egg-info/namespace_packages.txt
src/collective.slick.egg-info/not-zip-safe
src/collective.slick.egg-info/requires.txt
src/collective.slick.egg-info/top_level.txt
src/collective/slick/__init__.py
src/collective/slick/configure.zcml
src/collective/slick/interfaces.py
src/collective/slick/setuphandlers.py
src/collective/slick/testing.py
src/collective/slick/upgrades.py
src/collective/slick/upgrades.zcml
src/collective/slick/browser/__init__.py
src/collective/slick/browser/configure.zcml
src/collective/slick/browser/static/bundle.js
src/collective/slick/browser/static/bundle.js.map
src/collective/slick/browser/static/bundle.min.js
src/collective/slick/browser/static/bundle.min.js.map
src/collective/slick/browser/static/import-slick.js
src/collective/slick/browser/static/slick.css
src/collective/slick/browser/static/slick.min.js
src/collective/slick/locales/collective.slick.pot
src/collective/slick/locales/update.sh
src/collective/slick/profiles/default/browserlayer.xml
src/collective/slick/profiles/default/metadata.xml
src/collective/slick/profiles/default/registry.xml
src/collective/slick/profiles/to1020/registry.xml
src/collective/slick/profiles/uninstall/browserlayer.xml
src/collective/slick/profiles/uninstall/registry.xml
src/collective/slick/tests/__init__.py
src/collective/slick/tests/test_robot.py
src/collective/slick/tests/test_setup.py
src/collective/slick/tests/robot/test_example.robot