Metadata-Version: 2.1
Name: collective.slick
Version: 0.2.0
Summary: Add slick carousel css and js resources to your Plone 5 site
Home-page: https://pypi.python.org/pypi/collective.slick
Author: RedTurtle
Author-email: sviluppoplone@redturtle.it
License: MIT
Keywords: Python Plone Slick Carousel Collective
Platform: UNKNOWN
Classifier: Environment :: Web Environment
Classifier: Framework :: Plone
Classifier: Framework :: Plone :: 5.0
Classifier: Framework :: Plone :: 5.1
Classifier: Programming Language :: Python
Classifier: Programming Language :: Python :: 2.7
Classifier: Operating System :: OS Independent
Classifier: License :: OSI Approved :: MIT License
Provides-Extra: test
